thc_net/__init__.py
thc_net/abstract_estimator.py
thc_net/classifier.py
thc_net/explain.py.old
thc_net/explainable_model/input_utils.py
thc_net/explainable_model/model.py
thc_net/explainable_model/random_utils.py
thc_net/image/pretrained_model.py
thc_net/image/tabular_preproc.py
thc_net/input_utils.py
thc_net/model_utils.py
thc_net/net_utils.py
thc_net/regressor.py
thc_net/safe_label_encoder.py
thc_net/utils.py
thc_net-0.2.0.dist-info/WHEEL
thc_net-0.2.0.dist-info/METADATA
thc_net-0.2.0.dist-info/RECORD
