Metadata-Version: 2.1
Name: thc-net
Version: 0.2.0
Summary: 
Author: Hartorn
Author-email: hartorn.github@gmail.com
Requires-Python: >=3.6.1
Classifier: Programming Language :: Python :: 3
Classifier: Programming Language :: Python :: 3.7
Classifier: Programming Language :: Python :: 3.8
Requires-Dist: scikit-learn (==0.23.1)
Requires-Dist: tensorflow (==2.2.0)
Requires-Dist: tensorflow-addons (==0.11.2)
